Metadata-Version: 1.0
Name: gaubin-distribution
Version: 0.1
Summary: Gaussian and Binomial distributions
Home-page: UNKNOWN
Author: Olawumi Abayomi
Author-email: olawumiabayomi@gmail.com
License: UNKNOWN
Platform: UNKNOWN
